odoo/addons/test_queue_job_batch/README.rst
odoo/addons/test_queue_job_batch/__init__.py
odoo/addons/test_queue_job_batch/__manifest__.py
odoo/addons/test_queue_job_batch/i18n/fr.po
odoo/addons/test_queue_job_batch/i18n/it.po
odoo/addons/test_queue_job_batch/i18n/test_queue_job_batch.pot
odoo/addons/test_queue_job_batch/readme/CONTRIBUTORS.md
odoo/addons/test_queue_job_batch/readme/CREDITS.md
odoo/addons/test_queue_job_batch/readme/DESCRIPTION.md
odoo/addons/test_queue_job_batch/static/description/icon.png
odoo/addons/test_queue_job_batch/static/description/icon.svg
odoo/addons/test_queue_job_batch/static/description/index.html
odoo/addons/test_queue_job_batch/tests/__init__.py
odoo/addons/test_queue_job_batch/tests/test_queue_job_batch.py
odoo_addon_test_queue_job_batch-18.0.1.0.0.3.dist-info/METADATA
odoo_addon_test_queue_job_batch-18.0.1.0.0.3.dist-info/WHEEL
odoo_addon_test_queue_job_batch-18.0.1.0.0.3.dist-info/top_level.txt
odoo_addon_test_queue_job_batch-18.0.1.0.0.3.dist-info/RECORD
