Metadata-Version: 2.1
Name: odoo-addon-test_queue_job_batch
Version: 18.0.1.0.0.3
Requires-Python: >=3.10
Requires-Dist: odoo-addon-queue_job_batch==18.0.*
Requires-Dist: odoo-addon-test_queue_job==18.0.*
Requires-Dist: odoo==18.0.*
Summary: Test Job Queue Batch
Home-page: https://github.com/OCA/queue
License: AGPL-3
Author: Creu Blanca,Odoo Community Association (OCA)
Author-email: support@odoo-community.org
Classifier: Programming Language :: Python
Classifier: Framework :: Odoo
Classifier: Framework :: Odoo :: 18.0
Classifier: License :: OSI Approved :: GNU Affero General Public License v3
